funpush/__init__.py
funpush/base/__init__.py
funpush/base/client.py
funpush/base/message.py
funpush/dingtalk/__init__.py
funpush/dingtalk/client.py
funpush/dingtalk/message.py
funpush/dingtalk/model.py
funpush/dingtalk/util.py
funpush/wechat/__init__.py
funpush-1.0.5.dist-info/METADATA
funpush-1.0.5.dist-info/WHEEL
funpush-1.0.5.dist-info/top_level.txt
funpush-1.0.5.dist-info/RECORD
