Metadata-Version: 2.4
Name: funpush
Version: 1.0.5
Summary: funpush
Author-email: 牛哥 <niuliangtao@qq.com>, farfarfun <farfarfun@qq.com>
Maintainer-email: 牛哥 <niuliangtao@qq.com>, farfarfun <farfarfun@qq.com>
Project-URL: Organization, https://github.com/farfarfun
Project-URL: Repository, https://github.com/farfarfun/funpush
Project-URL: Releases, https://github.com/farfarfun/funpush/releases
Requires-Python: >=3.9
Requires-Dist: funutil>=1.0.53
